setup.py
django_realtime_ticket.egg-info/PKG-INFO
django_realtime_ticket.egg-info/SOURCES.txt
django_realtime_ticket.egg-info/dependency_links.txt
django_realtime_ticket.egg-info/requires.txt
django_realtime_ticket.egg-info/top_level.txt
realtime_ticket/__init__.py
realtime_ticket/middleware.py
realtime_ticket/models.py
realtime_ticket/urls.py
realtime_ticket/views.py