Metadata-Version: 1.0
Name: django-realtime-ticket
Version: 0.1.0
Summary: authorize django users in realtime(asynchronous) backends using expiring tickets in Redis
Home-page: https://github.com/FZambia/django-realtime-ticket
Author: Alexandr Emelin
Author-email: frvzmb@gmail.com
License: http://www.apache.org/licenses/LICENSE-2.0
Keywords: python django realtime asynchronous async ticket redis authorization
Platform: UNKNOWN
